notfound/__init__.py
notfound/extension.py
notfound/utils.py
sphinx_notfound_page-1.0.3.dist-info/LICENSE
sphinx_notfound_page-1.0.3.dist-info/WHEEL
sphinx_notfound_page-1.0.3.dist-info/METADATA
sphinx_notfound_page-1.0.3.dist-info/RECORD
