Metadata-Version: 2.1
Name: sphinx-notfound-page
Version: 1.0.3
Summary: Sphinx extension to build a 404 page with absolute URLs
Keywords: notfound,404,page,sphinx,documentation
Author-email: Manuel Kaufmann <humitos@gmail.com>
Requires-Python: >=3.8
Classifier: Development Status :: 5 - Production/Stable
Classifier: Framework :: Sphinx
Classifier: Framework :: Sphinx :: Extension
Classifier: License :: OSI Approved :: MIT License
Classifier: Operating System :: OS Independent
Classifier: Programming Language :: Python :: 3
Classifier: Programming Language :: Python :: 3 :: Only
Classifier: Programming Language :: Python :: 3.8
Classifier: Programming Language :: Python :: 3.9
Classifier: Programming Language :: Python :: 3.10
Classifier: Programming Language :: Python :: 3.11
Classifier: Programming Language :: Python :: 3.12
Classifier: Topic :: Documentation :: Sphinx
Classifier: Topic :: Software Development :: Documentation
Requires-Dist: sphinx>=5
Requires-Dist: sphinx-tabs ; extra == "doc"
Requires-Dist: sphinx-rtd-theme ; extra == "doc"
Requires-Dist: sphinxemoji ; extra == "doc"
Requires-Dist: sphinx-autoapi ; extra == "doc"
Requires-Dist: tox ; extra == "test"
Project-URL: Documentation, https://sphinx-notfound-page.readthedocs.io/
Project-URL: Source, https://github.com/readthedocs/sphinx-notfound-page
Project-URL: Tracker, https://github.com/readthedocs/sphinx-notfound-page/issues
Provides-Extra: doc
Provides-Extra: test
